nodegam/__init__.py
nodegam/arch.py
nodegam/data.py
nodegam/mypreprocessor.py
nodegam/nn_utils.py
nodegam/odst.py
nodegam/recorder.py
nodegam/sklearn.py
nodegam/trainer.py
nodegam/utils.py
nodegam/vis_utils.py
nodegam/gams/EncodingBase.py
nodegam/gams/MyBagging.py
nodegam/gams/MyBaselines.py
nodegam/gams/MyEBM.py
nodegam/gams/MySpline.py
nodegam/gams/MyXGB.py
nodegam/gams/__init__.py
nodegam/gams/base.py
nodegam/gams/general_utils.py
nodegam/gams/model_utils.py
nodegam/gams/utils.py
nodegam-0.3.0.dist-info/LICENSE.md
nodegam-0.3.0.dist-info/METADATA
nodegam-0.3.0.dist-info/WHEEL
nodegam-0.3.0.dist-info/top_level.txt
nodegam-0.3.0.dist-info/RECORD
