Metadata-Version: 2.1
Name: nodegam
Version: 0.3.0
Summary: NodeGAM - an interpretable deep learning GAM model.
Home-page: https://github.com/zzzace2000/nodegam
Author: Chun-Hao Chang
Author-email: chkchang21@gmail.com
License: UNKNOWN
Platform: UNKNOWN
Classifier: Programming Language :: Python :: 3.6
Classifier: Programming Language :: Python :: 3.7
Classifier: Programming Language :: Python :: 3.8
Classifier: Development Status :: 3 - Alpha
Classifier: License :: OSI Approved :: MIT License
Classifier: Operating System :: OS Independent
License-File: LICENSE.md
Requires-Dist: torch (>=1.1.0)
Requires-Dist: numpy (>=0.13)
Requires-Dist: scipy (>=1.2.0)
Requires-Dist: scikit-learn (>=0.17)
Requires-Dist: catboost (>=0.12.2)
Requires-Dist: xgboost (>=0.81)
Requires-Dist: matplotlib
Requires-Dist: tqdm
Requires-Dist: tensorboardX
Requires-Dist: pandas
Requires-Dist: prefetch-generator
Requires-Dist: requests
Requires-Dist: category-encoders
Requires-Dist: filelock
Requires-Dist: qhoptim
Requires-Dist: mat4py
Requires-Dist: interpret (>=0.2)
Requires-Dist: pygam
Requires-Dist: seaborn
